luna/common/CodeTimer.py
luna/common/Neo4jConnection.py
luna/common/Node.py
luna/common/PipelineBuilder.py
luna/common/__init__.py
luna/common/adapters.py
luna/common/config.py
luna/common/constants.py
luna/common/custom_logger.py
luna/common/dask.py
luna/common/sparksession.py
luna/common/stats.py
luna/common/utils.py
tests/__init__.py
tests/luna/__init__.py
tests/luna/common/__init__.py
tests/luna/common/another_test_config.yml
tests/luna/common/test_config.py
tests/luna/common/test_config.yml
tests/luna/common/test_constants.py
tests/luna/common/test_data_ingestion_template.yml
tests/luna/common/test_graph_enum.py
tests/luna/common/test_logger.py
tests/luna/common/test_utils.py
tests/luna/common/testdata/data_ingestion_template_invalid.yml
tests/luna/common/testdata/data_ingestion_template_valid.yml
tests/luna/common/testdata/data_ingestion_template_valid_empty_dataset.yml
tests/luna/common/testdata/data_ingestion_template_valid_empty_dataset_2.yml
tests/luna/common/testdata/geojson_data.yaml
tests/luna/common/testdata/simple_output_directory/metadata.yml
pyluna_common-0.3.3.dist-info/METADATA
pyluna_common-0.3.3.dist-info/WHEEL
pyluna_common-0.3.3.dist-info/top_level.txt
pyluna_common-0.3.3.dist-info/zip-safe
pyluna_common-0.3.3.dist-info/RECORD
