Metadata-Version: 2.1
Name: pyluna-common
Version: 0.3.3
Summary: Transformation functions and services for multi-modal oncology data
Home-page: https://componcmsk.org/msk-mind/
Author: msk-mind
Author-email: CompOncBST@mskcc.org
License: Apache License version 2.0
Project-URL: Bug Tracker, https://github.com/msk-mind/luna/issues
Keywords: radiology,pathology,clinical
Platform: UNKNOWN
Classifier: Framework :: Pytest
Classifier: Development Status :: 3 - Alpha
Classifier: License :: OSI Approved :: Apache Software License
Classifier: Operating System :: OS Independent
Classifier: Programming Language :: Python :: 3
Classifier: Programming Language :: Python :: 3.6
Classifier: Programming Language :: Python :: 3.7
Classifier: Topic :: Scientific/Engineering :: Artificial Intelligence
Requires-Dist: dask[complete]
Requires-Dist: bokeh (>=2.3.0)
Requires-Dist: click
Requires-Dist: decorator (<5.0,>=4.3)
Requires-Dist: filehash
Requires-Dist: joblib
Requires-Dist: minio
Requires-Dist: numpy
Requires-Dist: pandas
Requires-Dist: pyarrow
Requires-Dist: tornado
Requires-Dist: PyYAML (>=5.4)
Requires-Dist: jsonpath-ng (>=1.5.2)
Requires-Dist: yamale
Requires-Dist: requests
Requires-Dist: dirhash
Requires-Dist: log4mongo
Requires-Dist: tqdm
Provides-Extra: dev
Requires-Dist: pytest ; extra == 'dev'
Requires-Dist: pytest-cov ; extra == 'dev'
Requires-Dist: pytest-mock ; extra == 'dev'
Requires-Dist: pytest-runner ; extra == 'dev'
Requires-Dist: testfixtures ; extra == 'dev'
Requires-Dist: requests-mock ; extra == 'dev'
Requires-Dist: mock ; extra == 'dev'
Requires-Dist: wheel (>=0.22) ; extra == 'dev'
Requires-Dist: pyinstaller (>=4.0) ; extra == 'dev'
Requires-Dist: poetry ; extra == 'dev'
Requires-Dist: python-semantic-release ; extra == 'dev'
Requires-Dist: m2r2 ; extra == 'dev'
Requires-Dist: twine ; extra == 'dev'
Requires-Dist: Sphinx ; extra == 'dev'
